number_comparator/__init__.py
number_comparator/comparisons.py
number_comparator/operations.py
number_comparator/data/__init__.py
number_comparator/data/colors.py
number_comparator/data/first_prime.py
number_comparator-0.0.5.post1.dist-info/LICENSE
number_comparator-0.0.5.post1.dist-info/METADATA
number_comparator-0.0.5.post1.dist-info/WHEEL
number_comparator-0.0.5.post1.dist-info/top_level.txt
number_comparator-0.0.5.post1.dist-info/RECORD
