Metadata-Version: 2.1
Name: number-comparator
Version: 0.0.5.post1
Summary: A numeric comparator package.
Home-page: https://github.com
Author: Diego Ramirez
Author-email: dr01191115@gmail.com
License: UNKNOWN
Keywords: numbers number comparations operations python
Platform: UNKNOWN
Classifier: Development Status :: 5 - Production/Stable
Classifier: Intended Audience :: Education
Classifier: Intended Audience :: Developers
Classifier: Topic :: Software Development :: Build Tools
Classifier: Topic :: Scientific/Engineering :: Mathematics
Classifier: Natural Language :: English
Classifier: Programming Language :: Python :: 3
Classifier: License :: OSI Approved :: MIT License
Classifier: Operating System :: OS Independent
Classifier: Topic :: Software Development
Classifier: Topic :: Software Development :: Libraries :: Python Modules
Requires-Python: >=3.7
